aiida_wannier90_workflows/__init__.py
aiida_wannier90_workflows/calculations/split.py
aiida_wannier90_workflows/cli/__init__.py
aiida_wannier90_workflows/cli/group.py
aiida_wannier90_workflows/cli/list.py
aiida_wannier90_workflows/cli/node.py
aiida_wannier90_workflows/cli/params.py
aiida_wannier90_workflows/cli/plot.py
aiida_wannier90_workflows/cli/root.py
aiida_wannier90_workflows/cli/statistics.py
aiida_wannier90_workflows/common/__init__.py
aiida_wannier90_workflows/common/types.py
aiida_wannier90_workflows/data/__init__.py
aiida_wannier90_workflows/data/structure.py
aiida_wannier90_workflows/parsers/split.py
aiida_wannier90_workflows/utils/__init__.py
aiida_wannier90_workflows/utils/code.py
aiida_wannier90_workflows/utils/collinear.py
aiida_wannier90_workflows/utils/kpoints.py
aiida_wannier90_workflows/utils/scdm.py
aiida_wannier90_workflows/utils/str.py
aiida_wannier90_workflows/utils/structure.py
aiida_wannier90_workflows/utils/bands/__init__.py
aiida_wannier90_workflows/utils/bands/collinear.py
aiida_wannier90_workflows/utils/bands/distance.py
aiida_wannier90_workflows/utils/parser/__init__.py
aiida_wannier90_workflows/utils/parser/bands.py
aiida_wannier90_workflows/utils/parser/center.py
aiida_wannier90_workflows/utils/parser/spread.py
aiida_wannier90_workflows/utils/pseudo/__init__.py
aiida_wannier90_workflows/utils/pseudo/upf.py
aiida_wannier90_workflows/utils/pseudo/data/__init__.py
aiida_wannier90_workflows/utils/pseudo/data/dojo_nc_fr.json
aiida_wannier90_workflows/utils/pseudo/data/semicore/PseudoDojo_0.4_LDA_SR_standard_upf.json
aiida_wannier90_workflows/utils/pseudo/data/semicore/PseudoDojo_0.4_LDA_SR_stringent_upf.json
aiida_wannier90_workflows/utils/pseudo/data/semicore/PseudoDojo_0.4_PBE_FR_standard_upf.json
aiida_wannier90_workflows/utils/pseudo/data/semicore/PseudoDojo_0.4_PBE_SR_standard_upf.json
aiida_wannier90_workflows/utils/pseudo/data/semicore/PseudoDojo_0.4_PBE_SR_stringent_upf.json
aiida_wannier90_workflows-2.5.0.dist-info/entry_points.txt
aiida_wannier90_workflows-2.5.0.dist-info/licenses/LICENSE.txt
aiida_wannier90_workflows-2.5.0.dist-info/WHEEL
aiida_wannier90_workflows-2.5.0.dist-info/METADATA
aiida_wannier90_workflows-2.5.0.dist-info/RECORD
