Metadata-Version: 2.4
Name: aiida-wannier90-workflows
Version: 2.5.0
Summary: Advanced AiiDA workflows for Wannier90
Keywords: aiida,plugin,wannier90
Author-email: The AiiDA team <developers@aiida.net>
Requires-Python: >=3.9
Classifier: Development Status :: 5 - Production/Stable
Classifier: Framework :: AiiDA
Classifier: Environment :: Plugins
Classifier: License :: Free To Use But Restricted
Classifier: Operating System :: POSIX :: Linux
Classifier: Operating System :: MacOS :: MacOS X
Classifier: Programming Language :: Python
Classifier: Programming Language :: Python :: 3.9
Classifier: Programming Language :: Python :: 3.10
Classifier: Programming Language :: Python :: 3.11
Classifier: Programming Language :: Python :: 3.12
Classifier: Natural Language :: English
Classifier: Topic :: Scientific/Engineering :: Physics
Classifier: Intended Audience :: Science/Research
License-File: LICENSE.txt
Requires-Dist: aiida-core>=2.0,<3
Requires-Dist: aiida-pseudo>=0.6
Requires-Dist: aiida-quantumespresso>=4.4
Requires-Dist: aiida-wannier90>=2.2
Requires-Dist: click>=8.0
Requires-Dist: colorama
Requires-Dist: pandas ; extra == "analysis"
Requires-Dist: tables ; extra == "analysis"
Requires-Dist: scikit-learn ; extra == "analysis"
Requires-Dist: typer[all] ; extra == "dev"
Requires-Dist: upf_tools~=0.1 ; extra == "dev"
Requires-Dist: rich ; extra == "dev"
Requires-Dist: typer ; extra == "dev"
Requires-Dist: upf-tools ; extra == "dev"
Requires-Dist: aiida-core~=2.5 ; extra == "docs"
Requires-Dist: docutils ; extra == "docs"
Requires-Dist: sphinx ; extra == "docs"
Requires-Dist: sphinx-copybutton ; extra == "docs"
Requires-Dist: sphinx-book-theme ; extra == "docs"
Requires-Dist: sphinx-click ; extra == "docs"
Requires-Dist: sphinxcontrib-contentui ; extra == "docs"
Requires-Dist: sphinxcontrib-details-directive ; extra == "docs"
Requires-Dist: furo ; extra == "docs"
Requires-Dist: markupsafe ; extra == "docs"
Requires-Dist: pre-commit ; extra == "pre-commit"
Requires-Dist: pylint>=3 ; extra == "pre-commit"
Requires-Dist: pytest ; extra == "tests"
Requires-Dist: pytest-cov ; extra == "tests"
Requires-Dist: pytest-regressions ; extra == "tests"
Requires-Dist: pgtest ; extra == "tests"
Project-URL: Documentation, https://aiida-wannier90-workflows.readthedocs.io
Project-URL: Source, https://github.com/aiidateam/aiida-wannier90-workflows
Provides-Extra: analysis
Provides-Extra: dev
Provides-Extra: docs
Provides-Extra: pre-commit
Provides-Extra: tests
